[
null,
{"id":1,"expanded":true,"name":"Lobby","order":1,"parentId":0,"scrollX":1012.4444444444445,"scrollY":584.4444444444445},
{"id":2,"expanded":false,"name":"Ice_map_monster","order":2,"parentId":1,"scrollX":1012.4444444444445,"scrollY":577.3333333333334},
{"id":3,"expanded":true,"name":"núi lửa","order":3,"parentId":1,"scrollX":1012.4444444444445,"scrollY":584.4444444444445},
null,
{"id":5,"expanded":false,"name":"Map thường","order":4,"parentId":1,"scrollX":1012.4444444444445,"scrollY":584.4444444444445}
]